{"1314bfd1.png":"170_1314bfd1.png","14181dgw.jpg":"2_14181dgw.jpg","1fb5dff9.png":"147_1fb5dff9.png","3283bd31.png":"64_3283bd31.png","3bac4dsg.png":"142_3bac4dsg.png","5052a9sg.jpg":"2_5052a9sg.jpg","600353sg.jpg":"78_600353sg.jpg","6080c43o.jpg":"143_6080c43o.jpg","742aac73.png":"92_742aac73.png","9a33032d.jpg":"39_9a33032d.jpg","9e98193i.jpg":"65_9e98193i.jpg","bbba9e-w.png":"170_bbba9e-w.png","d69cffsg.jpg":"104_d69cffsg.jpg","e4fffa3i.jpg":"65_e4fffa3i.jpg","fbcddbmk.jpg":"131_fbcddbmk.jpg"}