{"078193i2.jpg":"72_078193i2.jpg","09aa15pm.jpg":"72_09aa15pm.jpg","0ed20cad.png":"92_0ed20cad.png","18d197av.jpg":"72_18d197av.jpg","28f1c7qb.png":"92_28f1c7qb.png","29f94e-y.jpg":"6_29f94e-y.jpg","2adfd938.jpg":"33_2adfd938.jpg","2ec997kl.jpg":"0_2ec997kl.jpg","3562c6d5.png":"92_3562c6d5.png","3da009gs.jpg":"69_3da009gs.jpg","4256c3kl.jpg":"0_4256c3kl.jpg","4ff5b0ga.jpg":"41_4ff5b0ga.jpg","6357fdsg.jpg":"90_6357fdsg.jpg","80b70e1w.png":"45_80b70e1w.png","87aec255.png":"55_87aec255.png","8a7785kl.jpg":"0_8a7785kl.jpg","9f3e55kl.jpg":"0_9f3e55kl.jpg","aca35f74.png":"0_aca35f74.png","af6c9237.png":"74_af6c9237.png","af80483j.jpg":"68_af80483j.jpg","b30d0c4y.png":"92_b30d0c4y.png","b5847dhe.jpg":"98_b5847dhe.jpg","b6dba6vp.png":"92_b6dba6vp.png","cf38a23j.jpg":"68_cf38a23j.jpg","d6be7c2p.jpg":"35_d6be7c2p.jpg","dd75e05i.jpg":"64_dd75e05i.jpg","df6216be.jpg":"64_df6216be.jpg","e01cackl.jpg":"0_e01cackl.jpg","e430332l.jpg":"10_e430332l.jpg","e5bfb63q.png":"92_e5bfb63q.png","f1627cga.jpg":"40_f1627cga.jpg"}