{"05af7aao.jpg":"0_05af7aao.jpg","0a05653i.jpg":"17_0a05653i.jpg","1f27d7cs.jpg":"40_1f27d7cs.jpg","1f8784sg.jpg":"0_1f8784sg.jpg","3283bd31.png":"32_3283bd31.png","3b8bcd3i.jpg":"17_3b8bcd3i.jpg","466c0acs.jpg":"40_466c0acs.jpg","55f4d23i.jpg":"40_55f4d23i.jpg","5b9bd2cs.jpg":"40_5b9bd2cs.jpg","709c483i.jpg":"40_709c483i.jpg","8180c1cs.jpg":"40_8180c1cs.jpg","979a6bsg.jpg":"0_979a6bsg.jpg","a000b6sg.jpg":"17_a000b6sg.jpg","b31b2bcs.jpg":"40_b31b2bcs.jpg","c8ab443i.jpg":"40_c8ab443i.jpg","d62dbdcs.jpg":"40_d62dbdcs.jpg","e66ab13i.jpg":"17_e66ab13i.jpg","e81e273i.jpg":"17_e81e273i.jpg","ed24dbcs.jpg":"40_ed24dbcs.jpg"}